seq_mult.sv
module multiplier(a,b,product,rst,clk,op_ready);
 input [3:0]a,b;
 input rst,clk;
 output reg op_ready;
 output reg[7:0]product;

 reg[7:0]temp,temp_b,p;

 assign temp={4'b0000,b};
 
 always @(posedge clk)
 begin
  
 if(rst==1'b1)
 begin
  op_ready = 1'b0;
  p=8'b0000_0000;
product=8'b0000_0000;
 end

 if(rst==1'b0)
  begin
   p = 8'b0000_0000;
   for(int i=0;i<4;i++)
    if(a[i]==1)
    begin
     temp_b = temp<<i;
    p = p+temp_b;

    if(i==3)
    op_ready = 1'b1;
    $display("p = %b", p);
  end
 end
//if(op_ready == 1'b1)
  product=p;
end
endmodule

seq_mult_tb.sv
module multiplier_tb();
 reg [3:0]a,b;
 reg rst,clk;
 wire op_ready;
 wire [7:0]product,temp,temp_b,p;
 multiplier dut(.*);
 initial 
 clk = 1'b0;
  always #5 clk=~clk; 
  
 initial begin
  rst = 1'b0; a=4'b0011; b=4'b1000; #10;
  rst = 1'b1;#10;

  rst=1'b0; a=4'b0111; b=4'b1001; #10;
  rst = 1'b1;#10;

  rst = 1'b0;a=4'b1011;b=4'b0111;#10;
  rst = 1'b1;#10;
   
  end
 initial begin

 $dumpfile("test.vcd");
 $dumpvars;

#70 $finish;

end
endmodule

test.vcd
$date
    Nov 28, 2022  14:31:20
$end
$version
    TOOL:	ncsim(64)	15.20-s086
$end
$timescale
    1 ns
$end

$scope module multiplier_tb $end
$var reg       4 !    a [3:0] $end
$var reg       4 "    b [3:0] $end
$var reg       1 #    rst  $end
$var reg       1 $    clk  $end
$var wire      1 %    op_ready  $end
$var wire      8 &    product [7:0] $end
$var wire      8 '    temp [7:0] $end
$var wire      8 (    temp_b [7:0] $end
$var wire      8 )    p [7:0] $end

$scope module dut $end
$var wire      4 *    a [3:0] $end
$var wire      4 +    b [3:0] $end
$var wire      1 ,    rst  $end
$var wire      1 -    clk  $end
$var reg       1 .    op_ready  $end
$var reg       8 /    product [7:0] $end
$var reg       8 0    temp [7:0] $end
$var reg       8 1    temp_b [7:0] $end
$var reg       8 2    p [7:0] $end
$upscope $end

$upscope $end

$enddefinitions $end
$dumpvars
b11 !
b1000 "
0#
0$
x%
bx &
bz '
bz (
bz )
b11 *
b1000 +
0,
0-
x.
bx /
b1000 0
bx 1
bx 2
$end
#5
1$
1-
b0 2
b1000 1
b1000 2
b10000 1
b11000 2
b11000 /
b11000 &
#10
1#
0$
0-
1,
#15
1$
1-
0.
b0 2
b0 /
b0 &
0%
#20
0#
b111 !
b1001 "
0$
0-
b1001 +
b111 *
0,
b1001 0
#25
1$
1-
b1001 1
b1001 2
b10010 1
b11011 2
b100100 1
b111111 2
b111111 /
b111111 &
#30
1#
0$
0-
1,
#35
1$
1-
b0 2
b0 /
b0 &
#40
0#
b1011 !
b111 "
0$
0-
b111 +
b1011 *
0,
b111 0
#45
1$
1-
b111 1
b111 2
b1110 1
b10101 2
b111000 1
b1001101 2
1.
b1001101 /
b1001101 &
1%
#50
1#
0$
0-
1,
#55
1$
1-
0.
b0 2
b0 /
b0 &
0%
